<?xml version="1.0" encoding="UTF-8" ?>
<?demandware-pipeline version="2.0"?>

<pipeline type="view">
  <branch basename="Profile">
    <segment>
      <node>
        <start-node name="Profile" secure="false"/>
        <node-display x="1" y="0"/>
      </node>
      <transition target-connector="in1" target-path="./+1"/>
    </segment>
    <segment>
      <node>
        <join-node/>
        <node-display x="0" y="1"/>
      </node>
      <simple-transition>
        <transition-display>
          <bend-point relative-to="source" x="0" y="1"/>
        </transition-display>
      </simple-transition>
      <node>
        <interaction-continue-node secure="false" start-name="ProfileForm" transaction-required="false">
          <template buffered="true" dynamic="false" name="profile"/>
        </interaction-continue-node>
        <node-display x="0" y="1"/>
        <branch basename="b2" source-connector="success">
          <transition target-connector="in">
            <transition-display>
              <bend-point relative-to="source" x="0" y="1"/>
            </transition-display>
          </transition>
          <segment>
            <node>
              <interaction-node transaction-required="false">
                <template buffered="true" dynamic="false"/>
              </interaction-node>
              <node-display x="0" y="1"/>
            </node>
          </segment>
        </branch>
      </node>
      <transition target-connector="in1" target-path="./+1"/>
    </segment>
    <segment>
      <node>
        <join-node/>
        <node-display x="-1" y="-1"/>
      </node>
      <transition target-connector="in1" target-path="./-1"/>
    </segment>
  </branch>
</pipeline>
